setup.cfg
setup.py
upkg/__init__.py
upkg/conf.py
upkg/upkg.py
upkg.egg-info/PKG-INFO
upkg.egg-info/SOURCES.txt
upkg.egg-info/dependency_links.txt
upkg.egg-info/entry_points.txt
upkg.egg-info/top_level.txt
upkg/cmds/__init__.py
upkg/cmds/base.py
upkg/cmds/build.py
upkg/cmds/depends.py
upkg/cmds/install.py
upkg/cmds/provides.py
upkg/cmds/push.py
upkg/cmds/query.py
upkg/cmds/remove.py
upkg/cmds/search.py
upkg/cmds/status.py
upkg/cmds/update.py
upkg/lib/Install.py
upkg/lib/__init__.py
upkg/lib/ctx.py
upkg/lib/pkgs_ioloop.py
upkg/lib/repo.py
upkg/lib/search/Search.py
upkg/lib/search/__init__.py