Metadata-Version: 1.0
Name: upkg
Version: 0.1.5
Summary: Package Yourself
Home-page: https://github.com/jeffbuttars/upkg
Author: Jeff Buttars
Author-email: jeff@jeffbuttars.com
License: GPLv2
Platform: UNKNOWN
